[
    {
        "features": [
            -1,
            -1,
            -1,
            -1,
            -1,
            97.5,
            -12.5
        ],
        "label": [
            0,
            0
        ]
    },
    {
        "features": [
            -1,
            -1,
            -1,
            -1,
            -1,
            97.5,
            -12.5
        ],
        "label": [
            0,
            0
        ]
    },
    {
        "features": [
            10.1,
            4.9,
            60.5,
            10.2,
            5.7,
            97.5,
            -12.5
        ],
        "label": [
            0,
            0
        ]
    },
    {
        "features": [
            8.8,
            6.2,
            60.4,
            8.6,
            4.5,
            97.5,
            -12.5
        ],
        "label": [
            0,
            0
        ]
    },
    {
        "features": [
            8.7,
            6.3,
            59.7,
            8.2,
            4.4,
            97.5,
            -12.5
        ],
        "label": [
            0,
            0
        ]
    },
    {
        "features": [
            8.4,
            6.3,
            59.8,
            8.4,
            4.8,
            97.5,
            -12.5
        ],
        "label": [
            0,
            0
        ]
    },
    {
        "features": [
            8.5,
            6.7,
            65.1,
            9.1,
            4.5,
            97.5,
            -12.5
        ],
        "label": [
            0,
            0
        ]
    },
    {
        "features": [
            8.9,
            6.4,
            59.0,
            8.5,
            4.5,
            97.5,
            -12.5
        ],
        "label": [
            0,
            0
        ]
    },
    {
        "features": [
            8.3,
            6.3,
            60.0,
            8.4,
            4.5,
            97.5,
            -12.5
        ],
        "label": [
            0,
            0
        ]
    },
    {
        "features": [
            8.6,
            6.3,
            59.9,
            8.4,
            4.8,
            97.5,
            -12.5
        ],
        "label": [
            0,
            0
        ]
    },
    {
        "features": [
            8.7,
            6.8,
            61.3,
            8.7,
            4.7,
            97.5,
            -12.5
        ],
        "label": [
            0,
            0
        ]
    },
    {
        "features": [
            8.6,
            6.6,
            62.1,
            8.8,
            4.8,
            97.5,
            -12.5
        ],
        "label": [
            0,
            0
        ]
    },
    {
        "features": [
            8.3,
            6.1,
            60.7,
            8.5,
            4.6,
            97.5,
            -12.5
        ],
        "label": [
            0,
            0
        ]
    },
    {
        "features": [
            8.2,
            6.2,
            62.3,
            8.8,
            4.6,
            97.5,
            -12.5
        ],
        "label": [
            0,
            0
        ]
    },
    {
        "features": [
            8.3,
            6.4,
            61.1,
            9.1,
            4.7,
            97.5,
            -12.5
        ],
        "label": [
            0,
            0
        ]
    },
    {
        "features": [
            8.6,
            6.1,
            62.6,
            9.0,
            4.5,
            97.5,
            -12.5
        ],
        "label": [
            0,
            0
        ]
    },
    {
        "features": [
            8.5,
            6.6,
            62.5,
            8.8,
            4.4,
            97.5,
            -12.5
        ],
        "label": [
            0,
            0
        ]
    },
    {
        "features": [
            8.6,
            6.2,
            63.0,
            8.4,
            4.7,
            97.5,
            -12.5
        ],
        "label": [
            0,
            0
        ]
    },
    {
        "features": [
            8.8,
            6.3,
            59.4,
            8.4,
            4.7,
            97.5,
            -12.5
        ],
        "label": [
            -20,
            20
        ]
    },
    {
        "features": [
            8.4,
            6.7,
            64.2,
            8.7,
            4.4,
            97.5,
            -12.5
        ],
        "label": [
            -20,
            20
        ]
    },
    {
        "features": [
            8.9,
            6.3,
            62.4,
            8.3,
            4.8,
            97.5,
            -12.5
        ],
        "label": [
            -20,
            20
        ]
    },
    {
        "features": [
            8.7,
            6.2,
            59.4,
            8.7,
            4.3,
            97.5,
            -12.5
        ],
        "label": [
            -20,
            20
        ]
    },
    {
        "features": [
            8.6,
            6.3,
            60.9,
            8.7,
            4.3,
            97.5,
            -12.5
        ],
        "label": [
            -20,
            20
        ]
    },
    {
        "features": [
            9.0,
            6.0,
            64.0,
            7.6,
            4.7,
            97.5,
            -12.5
        ],
        "label": [
            -20,
            20
        ]
    },
    {
        "features": [
            9.9,
            5.9,
            63.6,
            8.0,
            4.6,
            97.5,
            -12.5
        ],
        "label": [
            -20,
            20
        ]
    },
    {
        "features": [
            10.9,
            5.2,
            61.4,
            7.1,
            4.7,
            97.5,
            -12.5
        ],
        "label": [
            -20,
            20
        ]
    },
    {
        "features": [
            11.7,
            4.8,
            42.8,
            7.1,
            4.8,
            97.5,
            -12.5
        ],
        "label": [
            -20,
            20
        ]
    },
    {
        "features": [
            11.6,
            4.8,
            32.6,
            6.2,
            4.8,
            97.5,
            -12.5
        ],
        "label": [
            -20,
            20
        ]
    },
    {
        "features": [
            14.9,
            4.4,
            24.7,
            5.9,
            5.2,
            97.5,
            -12.5
        ],
        "label": [
            -20,
            20
        ]
    },
    {
        "features": [
            16.3,
            3.8,
            19.4,
            5.6,
            5.4,
            97.5,
            -12.5
        ],
        "label": [
            -20,
            20
        ]
    },
    {
        "features": [
            21.2,
            3.2,
            15.8,
            5.5,
            5.5,
            97.5,
            -12.5
        ],
        "label": [
            -20,
            20
        ]
    },
    {
        "features": [
            24.0,
            3.6,
            12.8,
            4.9,
            5.7,
            97.5,
            -12.5
        ],
        "label": [
            40,
            40
        ]
    },
    {
        "features": [
            33.2,
            3.2,
            11.5,
            4.9,
            6.1,
            97.5,
            -12.5
        ],
        "label": [
            40,
            40
        ]
    },
    {
        "features": [
            46.4,
            3.2,
            9.7,
            5.0,
            6.6,
            97.5,
            -12.5
        ],
        "label": [
            40,
            40
        ]
    },
    {
        "features": [
            60.8,
            3.3,
            7.9,
            4.8,
            7.1,
            97.5,
            -12.5
        ],
        "label": [
            40,
            40
        ]
    },
    {
        "features": [
            60.8,
            3.0,
            7.2,
            4.6,
            7.9,
            97.5,
            -12.5
        ],
        "label": [
            40,
            40
        ]
    },
    {
        "features": [
            60.5,
            3.2,
            6.6,
            4.3,
            8.1,
            97.5,
            -12.5
        ],
        "label": [
            40,
            40
        ]
    },
    {
        "features": [
            61.4,
            3.1,
            6.2,
            4.3,
            8.2,
            97.5,
            -12.5
        ],
        "label": [
            40,
            40
        ]
    },
    {
        "features": [
            62.8,
            3.2,
            6.3,
            4.5,
            8.6,
            97.5,
            -12.5
        ],
        "label": [
            40,
            40
        ]
    },
    {
        "features": [
            62.6,
            3.1,
            6.1,
            4.3,
            9.4,
            97.5,
            -12.5
        ],
        "label": [
            40,
            40
        ]
    },
    {
        "features": [
            61.8,
            3.4,
            6.3,
            4.3,
            9.2,
            97.5,
            -12.5
        ],
        "label": [
            60,
            20
        ]
    },
    {
        "features": [
            57.8,
            3.3,
            5.9,
            4.6,
            9.1,
            97.5,
            -12.5
        ],
        "label": [
            60,
            20
        ]
    },
    {
        "features": [
            59.5,
            3.2,
            6.0,
            4.5,
            9.1,
            97.5,
            -12.5
        ],
        "label": [
            60,
            20
        ]
    },
    {
        "features": [
            58.6,
            3.1,
            5.3,
            4.6,
            9.0,
            97.5,
            -12.5
        ],
        "label": [
            60,
            20
        ]
    },
    {
        "features": [
            60.0,
            2.3,
            5.1,
            4.4,
            8.8,
            97.5,
            -12.5
        ],
        "label": [
            60,
            20
        ]
    },
    {
        "features": [
            59.4,
            3.1,
            6.0,
            4.5,
            9.0,
            97.5,
            -12.5
        ],
        "label": [
            60,
            20
        ]
    },
    {
        "features": [
            54.2,
            3.2,
            6.2,
            4.6,
            8.4,
            97.5,
            -12.5
        ],
        "label": [
            60,
            20
        ]
    },
    {
        "features": [
            58.0,
            3.1,
            6.4,
            4.5,
            8.4,
            97.5,
            -12.5
        ],
        "label": [
            60,
            20
        ]
    },
    {
        "features": [
            56.7,
            3.1,
            6.4,
            4.8,
            8.0,
            97.5,
            -12.5
        ],
        "label": [
            60,
            20
        ]
    },
    {
        "features": [
            54.2,
            3.0,
            7.0,
            4.4,
            8.0,
            97.5,
            -12.5
        ],
        "label": [
            60,
            20
        ]
    },
    {
        "features": [
            56.8,
            2.9,
            7.4,
            4.5,
            7.4,
            97.5,
            -12.5
        ],
        "label": [
            60,
            20
        ]
    },
    {
        "features": [
            53.2,
            3.1,
            7.6,
            4.9,
            7.6,
            97.5,
            -12.5
        ],
        "label": [
            60,
            20
        ]
    },
    {
        "features": [
            54.7,
            3.3,
            6.9,
            4.8,
            6.9,
            97.5,
            -12.5
        ],
        "label": [
            60,
            20
        ]
    },
    {
        "features": [
            57.0,
            3.1,
            9.1,
            4.5,
            6.7,
            97.5,
            -12.5
        ],
        "label": [
            60,
            20
        ]
    },
    {
        "features": [
            52.5,
            2.9,
            9.5,
            4.5,
            6.5,
            97.5,
            -12.5
        ],
        "label": [
            60,
            20
        ]
    },
    {
        "features": [
            56.4,
            3.4,
            10.0,
            4.6,
            5.9,
            97.5,
            -12.5
        ],
        "label": [
            60,
            20
        ]
    },
    {
        "features": [
            35.9,
            3.7,
            11.3,
            4.6,
            6.0,
            97.5,
            -12.5
        ],
        "label": [
            40,
            40
        ]
    },
    {
        "features": [
            31.4,
            3.6,
            10.8,
            4.5,
            5.7,
            97.5,
            -12.5
        ],
        "label": [
            40,
            40
        ]
    },
    {
        "features": [
            26.5,
            3.8,
            13.6,
            4.4,
            5.2,
            97.5,
            -12.5
        ],
        "label": [
            40,
            40
        ]
    },
    {
        "features": [
            23.8,
            4.2,
            14.2,
            4.5,
            5.2,
            97.5,
            -12.5
        ],
        "label": [
            40,
            40
        ]
    },
    {
        "features": [
            23.5,
            4.0,
            14.0,
            4.4,
            4.8,
            97.5,
            -12.5
        ],
        "label": [
            40,
            40
        ]
    },
    {
        "features": [
            22.5,
            4.3,
            14.7,
            4.1,
            5.0,
            97.5,
            -12.5
        ],
        "label": [
            40,
            40
        ]
    },
    {
        "features": [
            21.6,
            4.4,
            14.8,
            4.1,
            4.5,
            97.5,
            -12.5
        ],
        "label": [
            20,
            60
        ]
    },
    {
        "features": [
            20.3,
            4.6,
            15.7,
            4.2,
            4.3,
            97.5,
            -12.5
        ],
        "label": [
            20,
            60
        ]
    },
    {
        "features": [
            19.7,
            4.9,
            16.9,
            3.7,
            4.2,
            97.5,
            -12.5
        ],
        "label": [
            20,
            60
        ]
    },
    {
        "features": [
            19.7,
            4.4,
            16.4,
            3.8,
            4.0,
            97.5,
            -12.5
        ],
        "label": [
            20,
            60
        ]
    },
    {
        "features": [
            20.9,
            5.0,
            16.4,
            3.6,
            3.8,
            97.5,
            -12.5
        ],
        "label": [
            20,
            60
        ]
    },
    {
        "features": [
            21.7,
            5.5,
            16.6,
            3.1,
            3.6,
            97.5,
            -12.5
        ],
        "label": [
            20,
            60
        ]
    },
    {
        "features": [
            22.3,
            5.5,
            16.1,
            3.1,
            3.9,
            97.5,
            -12.5
        ],
        "label": [
            20,
            60
        ]
    },
    {
        "features": [
            23.6,
            5.7,
            14.8,
            2.5,
            3.5,
            97.5,
            -12.5
        ],
        "label": [
            20,
            60
        ]
    },
    {
        "features": [
            25.1,
            5.7,
            14.7,
            2.6,
            3.6,
            97.5,
            -12.5
        ],
        "label": [
            20,
            60
        ]
    },
    {
        "features": [
            26.9,
            5.5,
            13.7,
            2.3,
            3.6,
            97.5,
            -12.5
        ],
        "label": [
            40,
            40
        ]
    },
    {
        "features": [
            44.4,
            6.0,
            14.3,
            2.2,
            3.4,
            97.5,
            -12.5
        ],
        "label": [
            40,
            40
        ]
    },
    {
        "features": [
            45.4,
            6.1,
            12.9,
            2.0,
            3.5,
            97.5,
            -12.5
        ],
        "label": [
            40,
            40
        ]
    },
    {
        "features": [
            44.2,
            6.2,
            12.6,
            1.9,
            3.5,
            97.5,
            -12.5
        ],
        "label": [
            20,
            60
        ]
    },
    {
        "features": [
            42.1,
            6.0,
            12.5,
            1.8,
            3.6,
            97.5,
            -12.5
        ],
        "label": [
            20,
            60
        ]
    },
    {
        "features": [
            43.1,
            5.9,
            13.3,
            1.7,
            3.3,
            97.5,
            -12.5
        ],
        "label": [
            20,
            60
        ]
    },
    {
        "features": [
            43.7,
            6.4,
            12.2,
            1.6,
            3.5,
            97.5,
            -12.5
        ],
        "label": [
            20,
            60
        ]
    },
    {
        "features": [
            43.0,
            6.1,
            12.2,
            1.5,
            3.6,
            97.5,
            -12.5
        ],
        "label": [
            20,
            60
        ]
    },
    {
        "features": [
            40.5,
            6.1,
            12.6,
            1.1,
            3.5,
            97.5,
            -12.5
        ],
        "label": [
            20,
            60
        ]
    },
    {
        "features": [
            39.0,
            6.5,
            11.5,
            1.0,
            3.7,
            97.5,
            -12.5
        ],
        "label": [
            40,
            40
        ]
    },
    {
        "features": [
            40.9,
            6.2,
            11.6,
            1.3,
            3.8,
            97.5,
            -12.5
        ],
        "label": [
            40,
            40
        ]
    },
    {
        "features": [
            40.5,
            6.6,
            11.1,
            1.3,
            3.8,
            97.5,
            -12.5
        ],
        "label": [
            40,
            40
        ]
    },
    {
        "features": [
            39.5,
            6.2,
            11.0,
            1.3,
            4.0,
            97.5,
            -12.5
        ],
        "label": [
            40,
            40
        ]
    },
    {
        "features": [
            39.6,
            6.2,
            10.7,
            1.2,
            4.2,
            97.5,
            -12.5
        ],
        "label": [
            40,
            40
        ]
    },
    {
        "features": [
            38.5,
            6.4,
            11.0,
            1.3,
            4.3,
            97.5,
            -12.5
        ],
        "label": [
            40,
            40
        ]
    },
    {
        "features": [
            38.5,
            5.9,
            10.6,
            1.2,
            4.2,
            97.5,
            -12.5
        ],
        "label": [
            40,
            40
        ]
    },
    {
        "features": [
            37.9,
            6.3,
            10.1,
            1.3,
            4.1,
            97.5,
            -12.5
        ],
        "label": [
            40,
            40
        ]
    },
    {
        "features": [
            37.7,
            6.6,
            10.3,
            1.3,
            4.3,
            97.5,
            -12.5
        ],
        "label": [
            40,
            40
        ]
    },
    {
        "features": [
            34.9,
            6.6,
            10.1,
            1.3,
            4.1,
            97.5,
            -12.5
        ],
        "label": [
            40,
            40
        ]
    },
    {
        "features": [
            34.4,
            6.7,
            10.6,
            1.2,
            4.1,
            97.5,
            -12.5
        ],
        "label": [
            40,
            40
        ]
    },
    {
        "features": [
            34.2,
            6.1,
            10.8,
            1.3,
            4.4,
            97.5,
            -12.5
        ],
        "label": [
            40,
            40
        ]
    },
    {
        "features": [
            35.8,
            6.5,
            10.7,
            1.2,
            4.4,
            97.5,
            -12.5
        ],
        "label": [
            40,
            40
        ]
    },
    {
        "features": [
            32.3,
            6.6,
            9.4,
            1.3,
            4.1,
            97.5,
            -12.5
        ],
        "label": [
            40,
            40
        ]
    },
    {
        "features": [
            33.1,
            6.3,
            9.0,
            1.3,
            4.7,
            97.5,
            -12.5
        ],
        "label": [
            40,
            40
        ]
    },
    {
        "features": [
            33.9,
            6.4,
            10.1,
            1.4,
            4.7,
            97.5,
            -12.5
        ],
        "label": [
            40,
            40
        ]
    },
    {
        "features": [
            31.7,
            6.5,
            10.3,
            1.5,
            4.4,
            97.5,
            -12.5
        ],
        "label": [
            40,
            40
        ]
    },
    {
        "features": [
            30.4,
            6.1,
            9.8,
            1.5,
            4.7,
            97.5,
            -12.5
        ],
        "label": [
            40,
            40
        ]
    },
    {
        "features": [
            31.7,
            6.2,
            9.9,
            1.4,
            4.4,
            97.5,
            -12.5
        ],
        "label": [
            40,
            40
        ]
    },
    {
        "features": [
            30.3,
            5.9,
            10.2,
            1.4,
            4.6,
            97.5,
            -12.5
        ],
        "label": [
            40,
            40
        ]
    },
    {
        "features": [
            29.6,
            5.7,
            9.9,
            1.6,
            4.6,
            97.5,
            -12.5
        ],
        "label": [
            40,
            40
        ]
    },
    {
        "features": [
            29.0,
            6.1,
            9.6,
            1.6,
            4.7,
            97.5,
            -12.5
        ],
        "label": [
            40,
            40
        ]
    },
    {
        "features": [
            28.0,
            6.0,
            9.9,
            1.5,
            4.6,
            97.5,
            -12.5
        ],
        "label": [
            40,
            40
        ]
    },
    {
        "features": [
            28.0,
            6.3,
            9.5,
            1.7,
            4.9,
            97.5,
            -12.5
        ],
        "label": [
            40,
            40
        ]
    },
    {
        "features": [
            27.3,
            5.9,
            9.5,
            1.7,
            4.7,
            97.5,
            -12.5
        ],
        "label": [
            40,
            40
        ]
    },
    {
        "features": [
            27.8,
            6.2,
            10.1,
            1.6,
            4.8,
            97.5,
            -12.5
        ],
        "label": [
            40,
            40
        ]
    },
    {
        "features": [
            27.4,
            6.1,
            9.4,
            1.7,
            4.4,
            97.5,
            -12.5
        ],
        "label": [
            40,
            40
        ]
    },
    {
        "features": [
            26.7,
            6.3,
            9.6,
            1.8,
            5.0,
            97.5,
            -12.5
        ],
        "label": [
            40,
            40
        ]
    },
    {
        "features": [
            24.7,
            5.8,
            8.6,
            1.7,
            4.9,
            97.5,
            -12.5
        ],
        "label": [
            40,
            40
        ]
    },
    {
        "features": [
            24.4,
            5.7,
            9.7,
            1.8,
            5.2,
            97.5,
            -12.5
        ],
        "label": [
            40,
            40
        ]
    },
    {
        "features": [
            24.6,
            5.8,
            9.4,
            1.7,
            5.1,
            97.5,
            -12.5
        ],
        "label": [
            40,
            40
        ]
    },
    {
        "features": [
            23.5,
            6.0,
            9.2,
            1.8,
            5.2,
            97.5,
            -12.5
        ],
        "label": [
            40,
            40
        ]
    },
    {
        "features": [
            24.5,
            5.6,
            9.5,
            1.8,
            5.1,
            97.5,
            -12.5
        ],
        "label": [
            40,
            40
        ]
    },
    {
        "features": [
            23.8,
            5.5,
            9.7,
            2.0,
            5.3,
            97.5,
            -12.5
        ],
        "label": [
            40,
            40
        ]
    },
    {
        "features": [
            21.4,
            5.3,
            9.4,
            2.0,
            5.3,
            97.5,
            -12.5
        ],
        "label": [
            40,
            40
        ]
    },
    {
        "features": [
            22.1,
            6.0,
            9.7,
            1.9,
            5.5,
            97.5,
            -12.5
        ],
        "label": [
            40,
            40
        ]
    },
    {
        "features": [
            22.5,
            5.5,
            9.7,
            2.0,
            5.6,
            97.5,
            -12.5
        ],
        "label": [
            40,
            40
        ]
    },
    {
        "features": [
            21.6,
            5.9,
            9.7,
            1.9,
            5.6,
            97.5,
            -12.5
        ],
        "label": [
            40,
            40
        ]
    },
    {
        "features": [
            20.2,
            5.8,
            9.1,
            1.6,
            5.2,
            97.5,
            -12.5
        ],
        "label": [
            40,
            40
        ]
    },
    {
        "features": [
            19.3,
            5.4,
            9.6,
            1.8,
            4.7,
            97.5,
            -12.5
        ],
        "label": [
            40,
            40
        ]
    },
    {
        "features": [
            19.3,
            5.5,
            8.8,
            2.0,
            27.9,
            97.5,
            -12.5
        ],
        "label": [
            40,
            40
        ]
    },
    {
        "features": [
            19.5,
            5.4,
            8.5,
            2.2,
            26.8,
            97.5,
            -12.5
        ],
        "label": [
            40,
            40
        ]
    },
    {
        "features": [
            19.0,
            5.5,
            8.2,
            2.1,
            25.3,
            97.5,
            -12.5
        ],
        "label": [
            40,
            40
        ]
    },
    {
        "features": [
            17.6,
            5.5,
            8.7,
            2.2,
            26.4,
            97.5,
            -12.5
        ],
        "label": [
            60,
            20
        ]
    },
    {
        "features": [
            18.1,
            5.4,
            9.3,
            2.2,
            24.6,
            97.5,
            -12.5
        ],
        "label": [
            60,
            20
        ]
    },
    {
        "features": [
            16.6,
            5.3,
            9.2,
            2.2,
            23.0,
            97.5,
            -12.5
        ],
        "label": [
            60,
            20
        ]
    },
    {
        "features": [
            15.8,
            5.2,
            8.8,
            2.3,
            24.6,
            97.5,
            -12.5
        ],
        "label": [
            60,
            20
        ]
    },
    {
        "features": [
            14.9,
            5.0,
            9.2,
            2.3,
            23.3,
            97.5,
            -12.5
        ],
        "label": [
            60,
            20
        ]
    },
    {
        "features": [
            14.7,
            5.7,
            9.6,
            2.2,
            22.5,
            97.5,
            -12.5
        ],
        "label": [
            60,
            20
        ]
    },
    {
        "features": [
            14.7,
            5.3,
            9.6,
            2.2,
            22.2,
            97.5,
            -12.5
        ],
        "label": [
            60,
            20
        ]
    },
    {
        "features": [
            13.7,
            5.3,
            10.2,
            2.4,
            23.2,
            97.5,
            -12.5
        ],
        "label": [
            60,
            20
        ]
    },
    {
        "features": [
            13.9,
            5.3,
            9.6,
            2.2,
            23.1,
            97.5,
            -12.5
        ],
        "label": [
            60,
            20
        ]
    },
    {
        "features": [
            12.6,
            5.2,
            11.2,
            2.4,
            22.2,
            97.5,
            -12.5
        ],
        "label": [
            60,
            20
        ]
    },
    {
        "features": [
            12.8,
            5.5,
            12.1,
            2.4,
            23.8,
            97.5,
            -12.5
        ],
        "label": [
            60,
            20
        ]
    },
    {
        "features": [
            11.9,
            5.7,
            12.2,
            2.4,
            23.3,
            97.5,
            -12.5
        ],
        "label": [
            60,
            20
        ]
    },
    {
        "features": [
            11.3,
            5.6,
            12.8,
            1.9,
            22.8,
            97.5,
            -12.5
        ],
        "label": [
            60,
            20
        ]
    },
    {
        "features": [
            11.0,
            5.0,
            13.7,
            2.0,
            23.9,
            97.5,
            -12.5
        ],
        "label": [
            60,
            20
        ]
    },
    {
        "features": [
            11.1,
            5.7,
            13.5,
            2.3,
            22.7,
            97.5,
            -12.5
        ],
        "label": [
            60,
            20
        ]
    },
    {
        "features": [
            10.6,
            5.7,
            12.7,
            5.9,
            23.4,
            97.5,
            -12.5
        ],
        "label": [
            60,
            20
        ]
    },
    {
        "features": [
            10.2,
            6.0,
            12.0,
            6.9,
            24.1,
            97.5,
            -12.5
        ],
        "label": [
            60,
            20
        ]
    },
    {
        "features": [
            9.8,
            6.4,
            10.6,
            7.2,
            26.0,
            97.5,
            -12.5
        ],
        "label": [
            60,
            20
        ]
    },
    {
        "features": [
            9.0,
            6.8,
            10.7,
            7.9,
            25.3,
            97.5,
            -12.5
        ],
        "label": [
            60,
            20
        ]
    },
    {
        "features": [
            9.1,
            6.6,
            9.5,
            8.8,
            25.6,
            97.5,
            -12.5
        ],
        "label": [
            60,
            20
        ]
    },
    {
        "features": [
            8.2,
            7.3,
            8.6,
            9.2,
            25.8,
            97.5,
            -12.5
        ],
        "label": [
            60,
            20
        ]
    },
    {
        "features": [
            7.9,
            6.8,
            8.0,
            9.4,
            27.5,
            97.5,
            -12.5
        ],
        "label": [
            60,
            20
        ]
    },
    {
        "features": [
            7.5,
            7.4,
            6.6,
            9.2,
            27.5,
            97.5,
            -12.5
        ],
        "label": [
            60,
            20
        ]
    },
    {
        "features": [
            7.7,
            8.0,
            6.5,
            9.6,
            28.4,
            97.5,
            -12.5
        ],
        "label": [
            60,
            20
        ]
    },
    {
        "features": [
            6.8,
            8.6,
            6.0,
            9.2,
            30.0,
            97.5,
            -12.5
        ],
        "label": [
            20,
            -20
        ]
    },
    {
        "features": [
            6.6,
            9.3,
            5.6,
            9.5,
            33.7,
            97.5,
            -12.5
        ],
        "label": [
            0,
            0
        ]
    },
    {
        "features": [
            6.4,
            9.8,
            4.9,
            9.5,
            35.0,
            97.5,
            -12.5
        ],
        "label": [
            0,
            0
        ]
    },
    {
        "features": [
            6.0,
            10.2,
            4.8,
            10.0,
            39.9,
            97.5,
            -12.5
        ],
        "label": [
            0,
            0
        ]
    },
    {
        "features": [
            6.0,
            9.8,
            4.3,
            10.3,
            42.0,
            97.5,
            -12.5
        ],
        "label": [
            -40,
            -40
        ]
    },
    {
        "features": [
            5.7,
            10.1,
            4.0,
            10.1,
            43.1,
            97.5,
            -12.5
        ],
        "label": [
            -40,
            -40
        ]
    },
    {
        "features": [
            5.8,
            10.0,
            3.9,
            9.5,
            47.3,
            97.5,
            -12.5
        ],
        "label": [
            -40,
            -40
        ]
    },
    {
        "features": [
            5.9,
            10.0,
            3.6,
            9.6,
            44.8,
            97.5,
            -12.5
        ],
        "label": [
            -40,
            -40
        ]
    },
    {
        "features": [
            5.7,
            9.7,
            3.9,
            10.1,
            47.3,
            97.5,
            -12.5
        ],
        "label": [
            -40,
            -40
        ]
    },
    {
        "features": [
            6.0,
            9.8,
            4.0,
            10.0,
            46.8,
            97.5,
            -12.5
        ],
        "label": [
            -40,
            -40
        ]
    },
    {
        "features": [
            5.9,
            10.2,
            4.3,
            10.2,
            47.9,
            97.5,
            -12.5
        ],
        "label": [
            -40,
            -40
        ]
    },
    {
        "features": [
            6.3,
            10.3,
            4.4,
            9.9,
            50.3,
            97.5,
            -12.5
        ],
        "label": [
            -40,
            -40
        ]
    },
    {
        "features": [
            6.9,
            9.8,
            4.7,
            8.6,
            54.4,
            97.5,
            -12.5
        ],
        "label": [
            -40,
            -40
        ]
    },
    {
        "features": [
            7.2,
            10.0,
            5.2,
            8.7,
            54.1,
            97.5,
            -12.5
        ],
        "label": [
            -40,
            -40
        ]
    },
    {
        "features": [
            7.5,
            9.7,
            5.2,
            7.7,
            57.0,
            97.5,
            -12.5
        ],
        "label": [
            -40,
            -40
        ]
    },
    {
        "features": [
            7.9,
            9.3,
            5.5,
            7.5,
            57.7,
            97.5,
            -12.5
        ],
        "label": [
            -40,
            -40
        ]
    },
    {
        "features": [
            8.4,
            8.9,
            6.3,
            6.8,
            59.1,
            97.5,
            -12.5
        ],
        "label": [
            -40,
            -40
        ]
    },
    {
        "features": [
            9.4,
            8.1,
            6.7,
            5.9,
            64.0,
            97.5,
            -12.5
        ],
        "label": [
            -40,
            -40
        ]
    },
    {
        "features": [
            9.1,
            8.0,
            7.0,
            5.3,
            63.6,
            97.5,
            -12.5
        ],
        "label": [
            0,
            0
        ]
    },
    {
        "features": [
            10.0,
            7.4,
            7.1,
            3.9,
            71.0,
            97.5,
            -12.5
        ],
        "label": [
            0,
            0
        ]
    },
    {
        "features": [
            10.9,
            7.1,
            7.6,
            3.6,
            72.7,
            97.5,
            -12.5
        ],
        "label": [
            0,
            0
        ]
    },
    {
        "features": [
            11.1,
            7.2,
            8.0,
            4.6,
            72.6,
            97.5,
            -12.5
        ],
        "label": [
            0,
            0
        ]
    },
    {
        "features": [
            11.2,
            6.4,
            7.8,
            5.3,
            73.1,
            97.5,
            -12.5
        ],
        "label": [
            60,
            20
        ]
    },
    {
        "features": [
            11.2,
            5.7,
            8.4,
            5.1,
            81.0,
            97.5,
            -12.5
        ],
        "label": [
            60,
            20
        ]
    },
    {
        "features": [
            11.7,
            5.8,
            8.5,
            5.6,
            81.0,
            97.5,
            -12.5
        ],
        "label": [
            60,
            20
        ]
    },
    {
        "features": [
            11.5,
            6.0,
            8.6,
            5.5,
            82.1,
            97.5,
            -12.5
        ],
        "label": [
            60,
            20
        ]
    },
    {
        "features": [
            11.6,
            6.3,
            8.4,
            5.7,
            79.9,
            97.5,
            -12.5
        ],
        "label": [
            60,
            20
        ]
    },
    {
        "features": [
            11.4,
            6.8,
            8.5,
            5.3,
            83.2,
            97.5,
            -12.5
        ],
        "label": [
            60,
            20
        ]
    },
    {
        "features": [
            11.7,
            7.4,
            8.3,
            5.6,
            82.0,
            97.5,
            -12.5
        ],
        "label": [
            60,
            20
        ]
    },
    {
        "features": [
            12.0,
            8.2,
            7.6,
            5.2,
            79.6,
            97.5,
            -12.5
        ],
        "label": [
            60,
            20
        ]
    },
    {
        "features": [
            11.2,
            8.5,
            7.9,
            5.1,
            80.4,
            97.5,
            -12.5
        ],
        "label": [
            60,
            20
        ]
    },
    {
        "features": [
            11.8,
            9.4,
            7.6,
            5.0,
            86.7,
            97.5,
            -12.5
        ],
        "label": [
            60,
            20
        ]
    },
    {
        "features": [
            12.2,
            9.3,
            7.0,
            4.9,
            87.6,
            97.5,
            -12.5
        ],
        "label": [
            60,
            20
        ]
    },
    {
        "features": [
            12.2,
            10.2,
            6.7,
            4.9,
            87.1,
            97.5,
            -12.5
        ],
        "label": [
            60,
            20
        ]
    },
    {
        "features": [
            11.3,
            10.2,
            6.1,
            3.9,
            93.4,
            97.5,
            -12.5
        ],
        "label": [
            60,
            20
        ]
    },
    {
        "features": [
            11.0,
            9.6,
            6.1,
            4.2,
            92.7,
            97.5,
            -12.5
        ],
        "label": [
            60,
            20
        ]
    },
    {
        "features": [
            11.3,
            9.0,
            5.7,
            3.9,
            68.3,
            97.5,
            -12.5
        ],
        "label": [
            60,
            20
        ]
    },
    {
        "features": [
            11.2,
            8.2,
            5.1,
            3.9,
            59.8,
            97.5,
            -12.5
        ],
        "label": [
            60,
            20
        ]
    },
    {
        "features": [
            11.4,
            7.5,
            4.8,
            4.5,
            46.4,
            97.5,
            -12.5
        ],
        "label": [
            60,
            20
        ]
    },
    {
        "features": [
            11.4,
            6.8,
            4.5,
            4.7,
            42.1,
            97.5,
            -12.5
        ],
        "label": [
            60,
            20
        ]
    },
    {
        "features": [
            11.2,
            6.0,
            4.4,
            4.9,
            36.8,
            97.5,
            -12.5
        ],
        "label": [
            60,
            20
        ]
    },
    {
        "features": [
            12.1,
            5.5,
            4.1,
            5.2,
            32.6,
            97.5,
            -12.5
        ],
        "label": [
            60,
            20
        ]
    },
    {
        "features": [
            12.0,
            5.0,
            3.8,
            5.6,
            31.9,
            97.5,
            -12.5
        ],
        "label": [
            60,
            20
        ]
    },
    {
        "features": [
            12.7,
            4.5,
            3.6,
            5.4,
            27.1,
            97.5,
            -12.5
        ],
        "label": [
            60,
            20
        ]
    },
    {
        "features": [
            12.9,
            4.2,
            3.5,
            5.7,
            26.6,
            97.5,
            -12.5
        ],
        "label": [
            60,
            20
        ]
    },
    {
        "features": [
            13.3,
            3.7,
            3.3,
            5.9,
            24.3,
            97.5,
            -12.5
        ],
        "label": [
            60,
            20
        ]
    },
    {
        "features": [
            13.8,
            3.3,
            3.2,
            5.8,
            22.8,
            97.5,
            -12.5
        ],
        "label": [
            60,
            20
        ]
    },
    {
        "features": [
            15.0,
            3.0,
            3.1,
            5.9,
            21.0,
            97.5,
            -12.5
        ],
        "label": [
            60,
            20
        ]
    },
    {
        "features": [
            14.1,
            2.4,
            3.2,
            5.6,
            18.5,
            97.5,
            -12.5
        ],
        "label": [
            60,
            20
        ]
    },
    {
        "features": [
            18.7,
            2.7,
            3.2,
            6.1,
            17.1,
            97.5,
            -12.5
        ],
        "label": [
            60,
            20
        ]
    },
    {
        "features": [
            20.8,
            2.4,
            2.8,
            6.2,
            16.3,
            97.5,
            -12.5
        ],
        "label": [
            60,
            20
        ]
    },
    {
        "features": [
            19.8,
            2.3,
            3.1,
            6.0,
            16.2,
            97.5,
            -12.5
        ],
        "label": [
            60,
            20
        ]
    },
    {
        "features": [
            26.8,
            2.0,
            3.2,
            6.1,
            14.8,
            97.5,
            -12.5
        ],
        "label": [
            60,
            20
        ]
    },
    {
        "features": [
            25.0,
            1.9,
            3.0,
            6.1,
            15.1,
            97.5,
            -12.5
        ],
        "label": [
            60,
            20
        ]
    },
    {
        "features": [
            33.0,
            1.8,
            3.1,
            6.4,
            14.0,
            97.5,
            -12.5
        ],
        "label": [
            60,
            20
        ]
    },
    {
        "features": [
            37.8,
            1.6,
            3.1,
            6.5,
            13.8,
            97.5,
            -12.5
        ],
        "label": [
            60,
            20
        ]
    },
    {
        "features": [
            43.9,
            1.5,
            3.3,
            6.5,
            13.0,
            97.5,
            -12.5
        ],
        "label": [
            60,
            20
        ]
    },
    {
        "features": [
            68.1,
            1.3,
            3.4,
            6.4,
            13.2,
            97.5,
            -12.5
        ],
        "label": [
            60,
            20
        ]
    },
    {
        "features": [
            66.1,
            0.5,
            3.5,
            6.5,
            12.8,
            97.5,
            -12.5
        ],
        "label": [
            60,
            20
        ]
    },
    {
        "features": [
            66.4,
            1.2,
            3.5,
            6.4,
            11.4,
            97.5,
            -12.5
        ],
        "label": [
            60,
            20
        ]
    },
    {
        "features": [
            71.7,
            1.2,
            3.4,
            6.7,
            11.7,
            97.5,
            -12.5
        ],
        "label": [
            60,
            20
        ]
    },
    {
        "features": [
            68.3,
            1.2,
            3.8,
            6.8,
            10.5,
            97.5,
            -12.5
        ],
        "label": [
            60,
            20
        ]
    },
    {
        "features": [
            70.4,
            1.1,
            4.2,
            6.8,
            10.2,
            97.5,
            -12.5
        ],
        "label": [
            40,
            40
        ]
    },
    {
        "features": [
            73.9,
            1.1,
            4.4,
            6.9,
            10.2,
            97.5,
            -12.5
        ],
        "label": [
            40,
            40
        ]
    },
    {
        "features": [
            75.4,
            1.2,
            4.5,
            6.6,
            10.2,
            97.5,
            -12.5
        ],
        "label": [
            40,
            40
        ]
    },
    {
        "features": [
            77.6,
            1.2,
            4.7,
            6.2,
            10.1,
            97.5,
            -12.5
        ],
        "label": [
            40,
            40
        ]
    },
    {
        "features": [
            77.7,
            1.3,
            4.7,
            6.5,
            9.5,
            97.5,
            -12.5
        ],
        "label": [
            40,
            40
        ]
    },
    {
        "features": [
            76.4,
            1.4,
            4.7,
            6.6,
            9.5,
            97.5,
            -12.5
        ],
        "label": [
            40,
            40
        ]
    },
    {
        "features": [
            73.6,
            1.5,
            4.9,
            6.5,
            9.7,
            97.5,
            -12.5
        ],
        "label": [
            40,
            40
        ]
    },
    {
        "features": [
            71.5,
            1.5,
            5.0,
            6.4,
            9.4,
            97.5,
            -12.5
        ],
        "label": [
            40,
            40
        ]
    },
    {
        "features": [
            71.7,
            1.6,
            5.0,
            6.2,
            9.2,
            97.5,
            -12.5
        ],
        "label": [
            40,
            40
        ]
    },
    {
        "features": [
            76.4,
            1.5,
            4.8,
            6.5,
            9.4,
            97.5,
            -12.5
        ],
        "label": [
            40,
            40
        ]
    },
    {
        "features": [
            75.3,
            1.6,
            5.5,
            5.8,
            9.0,
            97.5,
            -12.5
        ],
        "label": [
            40,
            40
        ]
    },
    {
        "features": [
            75.2,
            1.7,
            5.4,
            5.9,
            9.1,
            97.5,
            -12.5
        ],
        "label": [
            40,
            40
        ]
    },
    {
        "features": [
            73.2,
            1.7,
            5.7,
            6.2,
            8.6,
            97.5,
            -12.5
        ],
        "label": [
            40,
            40
        ]
    },
    {
        "features": [
            69.8,
            1.8,
            5.8,
            6.2,
            8.7,
            97.5,
            -12.5
        ],
        "label": [
            40,
            40
        ]
    },
    {
        "features": [
            71.9,
            1.9,
            5.5,
            5.8,
            9.0,
            97.5,
            -12.5
        ],
        "label": [
            40,
            40
        ]
    },
    {
        "features": [
            68.0,
            1.8,
            6.0,
            5.9,
            9.5,
            97.5,
            -12.5
        ],
        "label": [
            40,
            40
        ]
    },
    {
        "features": [
            71.4,
            1.9,
            5.7,
            6.0,
            9.3,
            97.5,
            -12.5
        ],
        "label": [
            40,
            40
        ]
    },
    {
        "features": [
            69.5,
            2.1,
            6.1,
            5.6,
            8.7,
            97.5,
            -12.5
        ],
        "label": [
            40,
            40
        ]
    },
    {
        "features": [
            70.5,
            2.0,
            6.3,
            5.7,
            9.0,
            97.5,
            -12.5
        ],
        "label": [
            40,
            40
        ]
    },
    {
        "features": [
            67.7,
            2.0,
            6.1,
            5.9,
            9.2,
            97.5,
            -12.5
        ],
        "label": [
            40,
            40
        ]
    },
    {
        "features": [
            66.6,
            2.1,
            6.0,
            5.4,
            9.1,
            97.5,
            -12.5
        ],
        "label": [
            40,
            40
        ]
    },
    {
        "features": [
            66.5,
            2.1,
            5.8,
            5.7,
            8.4,
            97.5,
            -12.5
        ],
        "label": [
            40,
            40
        ]
    },
    {
        "features": [
            69.1,
            1.8,
            6.6,
            5.5,
            8.6,
            97.5,
            -12.5
        ],
        "label": [
            40,
            40
        ]
    },
    {
        "features": [
            65.1,
            2.2,
            6.6,
            5.7,
            8.5,
            97.5,
            -12.5
        ],
        "label": [
            40,
            40
        ]
    },
    {
        "features": [
            66.5,
            2.2,
            6.2,
            5.6,
            8.6,
            97.5,
            -12.5
        ],
        "label": [
            40,
            40
        ]
    },
    {
        "features": [
            65.4,
            2.3,
            6.7,
            5.5,
            8.7,
            97.5,
            -12.5
        ],
        "label": [
            40,
            40
        ]
    },
    {
        "features": [
            64.4,
            2.5,
            6.9,
            5.3,
            8.2,
            97.5,
            -12.5
        ],
        "label": [
            40,
            40
        ]
    },
    {
        "features": [
            64.7,
            2.5,
            6.9,
            5.2,
            8.4,
            97.5,
            -12.5
        ],
        "label": [
            40,
            40
        ]
    },
    {
        "features": [
            60.4,
            2.5,
            6.5,
            5.4,
            7.6,
            97.5,
            -12.5
        ],
        "label": [
            40,
            40
        ]
    },
    {
        "features": [
            61.7,
            2.7,
            6.7,
            5.0,
            8.2,
            97.5,
            -12.5
        ],
        "label": [
            40,
            40
        ]
    },
    {
        "features": [
            60.3,
            2.7,
            7.2,
            5.2,
            8.2,
            97.5,
            -12.5
        ],
        "label": [
            40,
            40
        ]
    },
    {
        "features": [
            62.5,
            2.6,
            7.1,
            5.2,
            8.1,
            97.5,
            -12.5
        ],
        "label": [
            40,
            40
        ]
    },
    {
        "features": [
            59.9,
            2.8,
            7.3,
            5.2,
            7.7,
            97.5,
            -12.5
        ],
        "label": [
            40,
            40
        ]
    },
    {
        "features": [
            57.4,
            2.7,
            6.5,
            5.0,
            7.7,
            97.5,
            -12.5
        ],
        "label": [
            40,
            40
        ]
    },
    {
        "features": [
            60.8,
            2.4,
            7.5,
            4.8,
            8.2,
            97.5,
            -12.5
        ],
        "label": [
            40,
            40
        ]
    },
    {
        "features": [
            58.9,
            2.2,
            7.6,
            4.7,
            8.1,
            97.5,
            -12.5
        ],
        "label": [
            40,
            40
        ]
    },
    {
        "features": [
            57.2,
            3.0,
            7.8,
            4.6,
            7.6,
            97.5,
            -12.5
        ],
        "label": [
            40,
            40
        ]
    },
    {
        "features": [
            56.7,
            3.0,
            7.5,
            4.7,
            7.8,
            97.5,
            -12.5
        ],
        "label": [
            40,
            40
        ]
    },
    {
        "features": [
            58.9,
            2.9,
            7.6,
            4.6,
            7.5,
            97.5,
            -12.5
        ],
        "label": [
            40,
            40
        ]
    },
    {
        "features": [
            57.8,
            3.2,
            7.4,
            4.5,
            7.4,
            97.5,
            -12.5
        ],
        "label": [
            40,
            40
        ]
    },
    {
        "features": [
            55.4,
            3.2,
            7.9,
            4.4,
            7.7,
            97.5,
            -12.5
        ],
        "label": [
            40,
            40
        ]
    },
    {
        "features": [
            55.1,
            3.3,
            7.5,
            4.6,
            7.5,
            97.5,
            -12.5
        ],
        "label": [
            40,
            40
        ]
    },
    {
        "features": [
            58.0,
            3.2,
            7.8,
            4.6,
            7.2,
            97.5,
            -12.5
        ],
        "label": [
            40,
            40
        ]
    },
    {
        "features": [
            56.9,
            3.3,
            7.7,
            4.5,
            6.9,
            97.5,
            -12.5
        ],
        "label": [
            40,
            40
        ]
    },
    {
        "features": [
            56.5,
            3.4,
            8.1,
            4.3,
            7.0,
            97.5,
            -12.5
        ],
        "label": [
            40,
            40
        ]
    },
    {
        "features": [
            52.3,
            3.4,
            8.0,
            4.0,
            7.3,
            97.5,
            -12.5
        ],
        "label": [
            40,
            40
        ]
    },
    {
        "features": [
            53.4,
            3.4,
            8.0,
            4.3,
            7.1,
            97.5,
            -12.5
        ],
        "label": [
            40,
            40
        ]
    },
    {
        "features": [
            55.0,
            3.4,
            8.0,
            4.1,
            7.1,
            97.5,
            -12.5
        ],
        "label": [
            40,
            40
        ]
    },
    {
        "features": [
            52.7,
            3.7,
            8.4,
            4.1,
            6.9,
            97.5,
            -12.5
        ],
        "label": [
            40,
            40
        ]
    },
    {
        "features": [
            51.1,
            3.3,
            8.9,
            4.3,
            6.9,
            97.5,
            -12.5
        ],
        "label": [
            40,
            40
        ]
    },
    {
        "features": [
            52.2,
            3.6,
            8.9,
            4.1,
            6.9,
            97.5,
            -12.5
        ],
        "label": [
            40,
            40
        ]
    },
    {
        "features": [
            51.6,
            3.8,
            8.7,
            4.2,
            6.9,
            97.5,
            -12.5
        ],
        "label": [
            40,
            40
        ]
    },
    {
        "features": [
            49.1,
            3.8,
            8.3,
            3.9,
            6.4,
            97.5,
            -12.5
        ],
        "label": [
            40,
            40
        ]
    },
    {
        "features": [
            50.0,
            3.9,
            9.1,
            3.8,
            6.7,
            97.5,
            -12.5
        ],
        "label": [
            40,
            40
        ]
    },
    {
        "features": [
            47.2,
            3.9,
            8.8,
            3.9,
            6.6,
            97.5,
            -12.5
        ],
        "label": [
            40,
            40
        ]
    },
    {
        "features": [
            49.1,
            4.0,
            8.5,
            4.0,
            6.2,
            97.5,
            -12.5
        ],
        "label": [
            40,
            40
        ]
    },
    {
        "features": [
            46.4,
            3.9,
            8.8,
            3.7,
            6.3,
            97.5,
            -12.5
        ],
        "label": [
            40,
            40
        ]
    },
    {
        "features": [
            45.4,
            4.1,
            8.5,
            3.9,
            6.0,
            97.5,
            -12.5
        ],
        "label": [
            40,
            40
        ]
    },
    {
        "features": [
            45.8,
            4.3,
            9.3,
            3.8,
            6.5,
            97.5,
            -12.5
        ],
        "label": [
            40,
            40
        ]
    },
    {
        "features": [
            44.8,
            3.9,
            9.6,
            3.5,
            6.1,
            97.5,
            -12.5
        ],
        "label": [
            40,
            40
        ]
    },
    {
        "features": [
            45.7,
            4.0,
            9.3,
            3.8,
            5.9,
            97.5,
            -12.5
        ],
        "label": [
            40,
            40
        ]
    },
    {
        "features": [
            45.3,
            4.1,
            9.0,
            3.7,
            6.0,
            97.5,
            -12.5
        ],
        "label": [
            20,
            60
        ]
    },
    {
        "features": [
            44.9,
            4.0,
            9.8,
            3.7,
            5.7,
            97.5,
            -12.5
        ],
        "label": [
            20,
            60
        ]
    },
    {
        "features": [
            45.2,
            4.2,
            9.4,
            3.3,
            5.7,
            97.5,
            -12.5
        ],
        "label": [
            20,
            60
        ]
    },
    {
        "features": [
            43.7,
            4.3,
            9.7,
            3.4,
            6.2,
            97.5,
            -12.5
        ],
        "label": [
            40,
            40
        ]
    },
    {
        "features": [
            43.4,
            4.3,
            8.9,
            3.2,
            6.2,
            97.5,
            -12.5
        ],
        "label": [
            40,
            40
        ]
    },
    {
        "features": [
            40.7,
            4.4,
            9.0,
            3.3,
            6.0,
            97.5,
            -12.5
        ],
        "label": [
            40,
            40
        ]
    },
    {
        "features": [
            38.3,
            4.3,
            9.2,
            3.2,
            6.4,
            97.5,
            -12.5
        ],
        "label": [
            40,
            40
        ]
    },
    {
        "features": [
            38.8,
            4.3,
            8.8,
            3.1,
            6.1,
            97.5,
            -12.5
        ],
        "label": [
            40,
            40
        ]
    },
    {
        "features": [
            36.8,
            4.4,
            8.4,
            3.0,
            6.4,
            97.5,
            -12.5
        ],
        "label": [
            40,
            40
        ]
    },
    {
        "features": [
            39.0,
            4.7,
            8.4,
            2.9,
            6.5,
            97.5,
            -12.5
        ],
        "label": [
            40,
            40
        ]
    },
    {
        "features": [
            35.7,
            4.5,
            8.8,
            3.0,
            6.1,
            97.5,
            -12.5
        ],
        "label": [
            40,
            40
        ]
    },
    {
        "features": [
            37.0,
            4.8,
            8.6,
            3.2,
            6.1,
            97.5,
            -12.5
        ],
        "label": [
            40,
            40
        ]
    },
    {
        "features": [
            36.2,
            4.7,
            8.8,
            3.1,
            6.0,
            97.5,
            -12.5
        ],
        "label": [
            40,
            40
        ]
    },
    {
        "features": [
            33.3,
            4.6,
            9.2,
            3.0,
            6.1,
            97.5,
            -12.5
        ],
        "label": [
            40,
            40
        ]
    },
    {
        "features": [
            33.3,
            4.8,
            9.2,
            3.0,
            6.2,
            97.5,
            -12.5
        ],
        "label": [
            40,
            40
        ]
    },
    {
        "features": [
            33.4,
            4.6,
            8.8,
            3.2,
            6.5,
            97.5,
            -12.5
        ],
        "label": [
            40,
            40
        ]
    },
    {
        "features": [
            32.8,
            4.3,
            8.7,
            2.9,
            6.1,
            97.5,
            -12.5
        ],
        "label": [
            40,
            40
        ]
    },
    {
        "features": [
            31.6,
            4.9,
            8.4,
            3.1,
            6.3,
            97.5,
            -12.5
        ],
        "label": [
            40,
            40
        ]
    },
    {
        "features": [
            31.0,
            4.8,
            8.6,
            2.9,
            6.0,
            97.5,
            -12.5
        ],
        "label": [
            40,
            40
        ]
    },
    {
        "features": [
            30.9,
            4.5,
            8.5,
            3.0,
            6.1,
            97.5,
            -12.5
        ],
        "label": [
            40,
            40
        ]
    },
    {
        "features": [
            31.9,
            4.5,
            8.9,
            3.1,
            6.3,
            97.5,
            -12.5
        ],
        "label": [
            40,
            40
        ]
    },
    {
        "features": [
            29.4,
            4.5,
            8.5,
            3.0,
            6.3,
            97.5,
            -12.5
        ],
        "label": [
            40,
            40
        ]
    },
    {
        "features": [
            31.2,
            4.7,
            9.0,
            2.8,
            5.7,
            97.5,
            -12.5
        ],
        "label": [
            40,
            40
        ]
    },
    {
        "features": [
            28.5,
            4.6,
            8.9,
            2.7,
            6.4,
            97.5,
            -12.5
        ],
        "label": [
            40,
            40
        ]
    },
    {
        "features": [
            28.5,
            4.6,
            9.1,
            3.0,
            5.9,
            97.5,
            -12.5
        ],
        "label": [
            40,
            40
        ]
    },
    {
        "features": [
            28.6,
            4.6,
            8.7,
            3.0,
            6.3,
            97.5,
            -12.5
        ],
        "label": [
            40,
            40
        ]
    },
    {
        "features": [
            28.0,
            4.7,
            9.1,
            2.9,
            6.0,
            97.5,
            -12.5
        ],
        "label": [
            40,
            40
        ]
    },
    {
        "features": [
            27.8,
            4.9,
            9.0,
            2.9,
            5.8,
            97.5,
            -12.5
        ],
        "label": [
            40,
            40
        ]
    },
    {
        "features": [
            27.3,
            4.6,
            9.3,
            2.9,
            6.1,
            97.5,
            -12.5
        ],
        "label": [
            40,
            40
        ]
    },
    {
        "features": [
            26.1,
            4.2,
            9.2,
            3.0,
            5.8,
            97.5,
            -12.5
        ],
        "label": [
            40,
            40
        ]
    }
]